aioconnect/__init__.py
aioconnect/azure_key_vault.py
aioconnect/helpers.py
aioconnect/impact_api.py
aioconnect-0.1.9.dist-info/LICENSE
aioconnect-0.1.9.dist-info/METADATA
aioconnect-0.1.9.dist-info/WHEEL
aioconnect-0.1.9.dist-info/top_level.txt
aioconnect-0.1.9.dist-info/RECORD
