Metadata-Version: 2.1
Name: aioconnect
Version: 0.1.9
Summary: AIO connect
Home-page: https://github.com/aioneers/aioconnect
Author: AIO
Author-email: maintainer@aioneers.com
License: MIT
Download-URL: https://github.com/aioneers/aioconnect/tags
Platform: UNKNOWN
Classifier: Programming Language :: Python :: 3
Classifier: License :: OSI Approved :: MIT License
Classifier: Operating System :: OS Independent
Requires-Python: >=3.7
Requires-Dist: azure-identity
Requires-Dist: azure-keyvault
Requires-Dist: nbsphinx
Requires-Dist: numpydoc
Requires-Dist: pandas
Requires-Dist: pydata-sphinx-theme
Requires-Dist: pytest
Requires-Dist: python-dotenv
Requires-Dist: requests
